chembl_regressor.py
chembl_regressor-0.0.1.dist-info/METADATA
chembl_regressor-0.0.1.dist-info/WHEEL
chembl_regressor-0.0.1.dist-info/entry_points.txt
chembl_regressor-0.0.1.dist-info/licenses/LICENSE
chembl_regressor-0.0.1.dist-info/RECORD
