Metadata-Version: 2.3
Name: chembl_regressor
Version: 0.0.1
Summary: A ChEMBL biological activity regression model
Project-URL: Homepage, https://github.com/pslacerda/chembl-regressor
Project-URL: Issues, https://github.com/pslacerda/chembl-regressor/issues
Author-email: Pedro Sousa Lacerda <pslacerda@gmail.com>
License: This is free and unencumbered software released into the public domain.
License-File: LICENSE
Classifier: Programming Language :: Python :: 3
Requires-Python: >=3.11
Requires-Dist: click
Requires-Dist: joblib
Requires-Dist: lightgbm
Requires-Dist: matplotlib
Requires-Dist: molfeat
Requires-Dist: numpy
Requires-Dist: scikit-learn
Requires-Dist: scipy
Requires-Dist: seaborn
